LICENSE
MANIFEST.in
README.rst
setup.cfg
setup.py
django_tinyforum.egg-info/PKG-INFO
django_tinyforum.egg-info/SOURCES.txt
django_tinyforum.egg-info/dependency_links.txt
django_tinyforum.egg-info/not-zip-safe
django_tinyforum.egg-info/requires.txt
django_tinyforum.egg-info/top_level.txt
tinyforum/__init__.py
tinyforum/admin.py
tinyforum/forms.py
tinyforum/models.py
tinyforum/signals.py
tinyforum/utils.py
tinyforum/views.py
tinyforum/templates/tinyforum/base.html
tinyforum/templates/tinyforum/pagination.html
tinyforum/templates/tinyforum/post_form.html
tinyforum/templates/tinyforum/post_list.html
tinyforum/templates/tinyforum/postreport_list.html
tinyforum/templates/tinyforum/report_form.html
tinyforum/templates/tinyforum/thread_form.html
tinyforum/templates/tinyforum/thread_list.html
tinyforum/templates/tinyforum/thread_star.html
tinyforum/templatetags/__init__.py
tinyforum/templatetags/tinyforum.py